Metadata-Version: 1.1
Name: ekomi-api-python
Version: 0.1
Summary: This package connect to EKOMI API.
Home-page: https://bitbucket.org/abalt/ekomi-api-python
Author: DNest
Author-email: admin@dnestagency.com
License: Copyright (c) 2011, Tangent Communications PLC and individual contributors.
